{
  "ids": {
    "business_id": "drbackflowtestingandrepair",
    "place_id": "ChIJO4kwAFk53QkRkArhcqhZ0BA",
    "google_id": "0x9dd39590030893b:0x10d059a872e10a90"
  },
  "basic_info": {
    "name": "DR Backflow Testing and Repair",
    "phone": "+1 479-325-4397",
    "query_name": "",
    "rating": "",
    "working_hours": "{\"Monday\": \"8AM-7PM\", \"Tuesday\": \"8AM-7PM\", \"Wednesday\": \"8AM-7PM\", \"Thursday\": \"8AM-7PM\", \"Friday\": \"8AM-7PM\", \"Saturday\": \"8AM-12PM\", \"Sunday\": \"Closed\"}",
    "business_status": "OPERATIONAL"
  },
  "location": {
    "full_address": "",
    "city": "",
    "state": "",
    "postal_code": "",
    "latitude": 35.987576,
    "longitude": -92.2301065
  },
  "review_trends": {
    "monthly_reviews": {},
    "yearly_totals": {},
    "total_reviews": "",
    "owner_responses": 0
  },
  "scores": {
    "photo_score": 0,
    "facebook_score": 0
  },
  "social_media": {
    "facebook": "",
    "instagram": "",
    "website": ""
  }
}